syllable_sdk/__init__.py
syllable_sdk/_hooks/__init__.py
syllable_sdk/_hooks/registration.py
syllable_sdk/_hooks/sdkhooks.py
syllable_sdk/_hooks/types.py
syllable_sdk/_version.py
syllable_sdk/agents.py
syllable_sdk/basesdk.py
syllable_sdk/batches.py
syllable_sdk/campaigns.py
syllable_sdk/channels.py
syllable_sdk/conversation_config.py
syllable_sdk/conversations.py
syllable_sdk/custom_messages.py
syllable_sdk/dashboards.py
syllable_sdk/data_sources.py
syllable_sdk/directory.py
syllable_sdk/errors/__init__.py
syllable_sdk/errors/apierror.py
syllable_sdk/errors/httpvalidationerror.py
syllable_sdk/errors/no_response_error.py
syllable_sdk/errors/responsevalidationerror.py
syllable_sdk/errors/syllablesdkerror.py
syllable_sdk/events.py
syllable_sdk/folders.py
syllable_sdk/full_summary.py
syllable_sdk/httpclient.py
syllable_sdk/incidents.py
syllable_sdk/insights_sdk.py
syllable_sdk/insights_tools.py
syllable_sdk/language_groups.py
syllable_sdk/latency.py
syllable_sdk/models/__init__.py
syllable_sdk/models/agent_deleteop.py
syllable_sdk/models/agent_get_by_idop.py
syllable_sdk/models/agent_listop.py
syllable_sdk/models/agentcreate.py
syllable_sdk/models/agentlanguage.py
syllable_sdk/models/agentproperties.py
syllable_sdk/models/agentresponse.py
syllable_sdk/models/agentsttprovider.py
syllable_sdk/models/agenttooldefaults.py
syllable_sdk/models/agenttoolfielddefault.py
syllable_sdk/models/agentupdate.py
syllable_sdk/models/agentvoice.py
syllable_sdk/models/agentvoicedisplayname.py
syllable_sdk/models/agentvoicegender.py
syllable_sdk/models/agentvoicemodel.py
syllable_sdk/models/agentvoicevarname.py
syllable_sdk/models/agentwaitsound.py
syllable_sdk/models/available_targetsop.py
syllable_sdk/models/availabletarget.py
syllable_sdk/models/availabletargetproperties.py
syllable_sdk/models/batchdetails.py
syllable_sdk/models/batchproperties.py
syllable_sdk/models/batchstatus.py
syllable_sdk/models/body_directory_member_bulk_load.py
syllable_sdk-0.44.20.dist-info/METADATA
syllable_sdk-0.44.20.dist-info/WHEEL
syllable_sdk-0.44.20.dist-info/RECORD
